{
  "id": "criminal_code_bih:187",
  "law_id": "criminal_code_bih",
  "article_number": "187",
  "title": "Međunarodno navođenje na prostituciju",
  "content_path": "../article-text/0187.txt",
  "paragraphs": [
    "(1) Ko radi zarade ili druge koristi navodi, podstiče ili namamljuje drugog na pružanje\nseksualnih usluga ili na drugi način omogući njegovu predaju drugome radi pružanja\nseksualnih usluga ili na bilo koji način učestvuje u organiziranju ili vođenju pružanja\nseksualnih usluga u državi u kojoj to lice nema prebivalište ili čiji nije državljanin kaznit\nće se kaznom zatvora u trajanju od šest mjeseci do pet godina.",
    "(2) Činjenica da se lice koje se navodi, podstiče ili namamljuje već bavilo prostitucijom\nne utiče na postojanje krivičnog djela."
  ],
  "keywords": [],
  "metadata": {
    "sort_key": "0187",
    "source_file": "criminal_code_bih.main-law.final.txt",
    "review_status": "draft_generated"
  }
}